meepmeep/__init__.py
meepmeep/knot2d.py
meepmeep/knots.py
meepmeep/newton.py
meepmeep/orbit.py
meepmeep/tsorbit.py
meepmeep/utils.py
meepmeep/version.py
meepmeep/xyz5.py
meepmeep/xy/__init__.py
meepmeep/xy/derivatives.py
meepmeep/xy/par_direct.py
meepmeep/xy/par_fitting.py
meepmeep/xy/position.py
meepmeep/xyz/__init__.py
meepmeep/xyz/position.py
meepmeep-0.7.2.dist-info/LICENSE
meepmeep-0.7.2.dist-info/METADATA
meepmeep-0.7.2.dist-info/WHEEL
meepmeep-0.7.2.dist-info/top_level.txt
meepmeep-0.7.2.dist-info/RECORD
